svety/__init__.py
svety/hellqvist.xml
svety/reader.py
svety/retriever.py
svety/tests.py
svety-1.0.0.dist-info/LICENSE
svety-1.0.0.dist-info/METADATA
svety-1.0.0.dist-info/WHEEL
svety-1.0.0.dist-info/top_level.txt
svety-1.0.0.dist-info/zip-safe
svety-1.0.0.dist-info/RECORD
