Metadata-Version: 2.1
Name: svety
Version: 1.0.0
Summary: Reader of a Swedish etymological dictionary
Home-page: https://github.com/clemsciences/svety
Author: Clément Besnier
Author-email: clemsciences@aol.com
License: License :: OSI Approved :: MIT License
Keywords: swedish,etymology,dictionary
Platform: UNKNOWN
Classifier: Programming Language :: Python :: 3
Classifier: Operating System :: OS Independent
Classifier: License :: OSI Approved :: MIT License
Classifier: Topic :: Text Processing
Classifier: Topic :: Text Processing :: Markup :: XML
Requires-Python: >=3.6
Requires-Dist: lxml
Requires-Dist: requests
